signalpilot_ai/__init__.py
signalpilot_ai/_version.py
signalpilot_ai/cache_handlers.py
signalpilot_ai/cache_service.py
signalpilot_ai/composio_handlers.py
signalpilot_ai/composio_service.py
signalpilot_ai/database_config_handlers.py
signalpilot_ai/database_config_service.py
signalpilot_ai/databricks_schema_service.py
signalpilot_ai/file_scanner_service.py
signalpilot_ai/handlers.py
signalpilot_ai/integrations_config.py
signalpilot_ai/kernel_provisioner.py
signalpilot_ai/log_utils.py
signalpilot_ai/mcp_handlers.py
signalpilot_ai/mcp_server_manager.py
signalpilot_ai/mcp_service.py
signalpilot_ai/oauth_token_store.py
signalpilot_ai/schema_search_config.yml
signalpilot_ai/schema_search_service.py
signalpilot_ai/signalpilot_home.py
signalpilot_ai/snowflake_schema_service.py
signalpilot_ai/test_dbt_mcp_server.py
signalpilot_ai/unified_database_schema_service.py
signalpilot_ai/html_export_template/README.md
signalpilot_ai/html_export_template/conf.json
signalpilot_ai/html_export_template/index.html.j2
signalpilot_ai/tests/__init__.py
signalpilot_ai/tests/test_handlers.py
signalpilot_ai-0.12.0.data/data/etc/jupyter/jupyter_server_config.d/signalpilot_ai.json
signalpilot_ai-0.12.0.data/data/share/jupyter/labextensions/signalpilot-ai/package.json
signalpilot_ai-0.12.0.data/data/share/jupyter/labextensions/signalpilot-ai/schemas/signalpilot-ai/package.json.orig
signalpilot_ai-0.12.0.data/data/share/jupyter/labextensions/signalpilot-ai/schemas/signalpilot-ai/plugin.json
signalpilot_ai-0.12.0.data/data/share/jupyter/labextensions/signalpilot-ai/static/110.de370cf52688f24aa409.js
signalpilot_ai-0.12.0.data/data/share/jupyter/labextensions/signalpilot-ai/static/122.7af1b8a8e84ef115e08d.js
signalpilot_ai-0.12.0.data/data/share/jupyter/labextensions/signalpilot-ai/static/129.b6874df95c9ed99a4852.js
signalpilot_ai-0.12.0.data/data/share/jupyter/labextensions/signalpilot-ai/static/220.f25fa4765901757fb9c5.js
signalpilot_ai-0.12.0.dist-info/METADATA
signalpilot_ai-0.12.0.dist-info/WHEEL
signalpilot_ai-0.12.0.dist-info/entry_points.txt
signalpilot_ai-0.12.0.dist-info/licenses/LICENSE
signalpilot_ai-0.12.0.dist-info/RECORD
